README.md
pyproject.toml
setup.cfg
setup.py
restdf/__init__.py
restdf/__main__.py
restdf.egg-info/PKG-INFO
restdf.egg-info/SOURCES.txt
restdf.egg-info/dependency_links.txt
restdf.egg-info/entry_points.txt
restdf.egg-info/requires.txt
restdf.egg-info/top_level.txt
restdf/configs/__init__.py
restdf/configs/config.py
restdf/configs/settings.py
restdf/routes/__init__.py
restdf/routes/flask_routes.py
restdf/routes/flask_schemas/__init__.py
restdf/routes/flask_schemas/metadata.py
restdf/routes/flask_schemas/models.py
restdf/routes/flask_schemas/utils.py
restdf/utils/__init__.py
restdf/utils/exceptions.py
restdf/utils/helper.py
restdf/utils/io.py
restdf/utils/utils.py