Metadata-Version: 2.1
Name: restdf
Version: 1.0.0
Summary: Create a simple API from a dataframe!
Home-page: https://github.com/Mukhopadhyay/restdf
Author: Pranesh Mukhopadhyay
Author-email: praneshmukherjee7@gmail.com
License: MIT
Project-URL: ReadTheDocs, https://restdf.readthedocs.io/en/latest/
Platform: UNKNOWN
Classifier: License :: OSI Approved :: MIT License
Classifier: Programming Language :: Python :: 3
Classifier: Programming Language :: Python :: 3.8
Classifier: Programming Language :: Python :: 3.9
